[

    {
        "id":0,
        "category":"food",
        "type":"burger",
        "name": "random food name",
        "description":"small description of the food plus the ingredients ingredient 1, ingredient 2, ingredient 3, ingredient 4, etc...",       
        "imgURL": "https://res.cloudinary.com/ivanscacloud/image/upload/v1672697215/goodfood/hamburger-e_kuxcuc.png",
        "price": 123
    },
    {
        "id":1,
        "category":"food",
        "type":"pizza",
        "name": "random food name",
        "description":"small description of the food plus the ingredients ingredient 1, ingredient 2, ingredient 3, ingredient 4, etc...",
        "ingredients": [
            "sdad",
            "asdasd",
            "sadasdsa",
            "asdasd"
        ],
        "imgURL": "https://res.cloudinary.com/ivanscacloud/image/upload/v1672697220/goodfood/pizza-e_lxdigr.png",
        "price": 435
    },
    {
        "id":2,
        "category":"food",
        "type":"pizza",
        "name": "random food name",
        "description":"small description of the food plus the ingredients ingredient 1, ingredient 2, ingredient 3, ingredient 4, etc...",
        "ingredients": [
            "sdad",
            "asdasd",
            "sadasdsa",
            "asdasd"
        ],
        "imgURL": "https://res.cloudinary.com/ivanscacloud/image/upload/v1672697220/goodfood/pizza-e_lxdigr.png",
        "price": 203
    },
    {
        "id":3,
        "category":"dessert",
        "type":"sundae",
        "name": "random food name",
        "description":"small description of the food plus the ingredients ingredient 1, ingredient 2, ingredient 3, ingredient 4, etc...",
        "ingredients": [
            "sdad",
            "asdasd",
            "sadasdsa",
            "asdasd"
        ],
        "imgURL": "https://res.cloudinary.com/ivanscacloud/image/upload/v1672697217/goodfood/dessert-e_a00x8q.png",
        "price": 178
    },
    {
        "id":4,
        "category":"drink",
        "type":"beer",
        "name": "random food name",
        "description":"small description of the food plus the ingredients ingredient 1, ingredient 2, ingredient 3, ingredient 4, etc...",
        "ingredients": [
            "sdad",
            "asdasd",
            "sadasdsa",
            "asdasd"
        ],
        "imgURL": "https://res.cloudinary.com/ivanscacloud/image/upload/v1672697212/goodfood/beer2-e_zmiacq.png",
        "price": 20
    },
    {
        "id":5,
        "category":"drink",
        "type":"beer",
        "name": "random food name",
        "description":"small description of the food plus the ingredients ingredient 1, ingredient 2, ingredient 3, ingredient 4, etc...",
        "ingredients": [
            "sdad",
            "asdasd",
            "sadasdsa",
            "asdasd"
        ],
        "imgURL": "https://res.cloudinary.com/ivanscacloud/image/upload/v1672697212/goodfood/beer3-e_babbne.png",
        "price": 20
    },
    {
        "id":6,
        "category":"food",
        "type":"burger",
        "name": "random food name",
        "description":"small description of the food plus the ingredients ingredient 1, ingredient 2, ingredient 3, ingredient 4, etc...",
        "ingredients": [
            "sdad",
            "asdasd",
            "sadasdsa",
            "asdasd"
        ],          
        "imgURL": "https://res.cloudinary.com/ivanscacloud/image/upload/v1672697212/goodfood/burger2-e_mcu2e2.png",
        "price": 123
    },
    {
        "id":7,
        "category":"food",
        "type":"burger",
        "name": "random food name",
        "description":"small description of the food plus the ingredients ingredient 1, ingredient 2, ingredient 3, ingredient 4, etc...",
        "ingredients": [
            "sdad",
            "asdasd",
            "sadasdsa",
            "asdasd"
        ],          
        "imgURL": "https://res.cloudinary.com/ivanscacloud/image/upload/v1672697212/goodfood/burger-e_berlqy.png",
        "price": 123
    },    
    {
        "id":8,
        "category":"food",
        "type":"pasta",
        "name": "random food name",
        "description":"small description of the food plus the ingredients ingredient 1, ingredient 2, ingredient 3, ingredient 4, etc...",
        "ingredients": [
            "sdad",
            "asdasd",
            "sadasdsa",
            "asdasd"
        ],
        "imgURL": "https://res.cloudinary.com/ivanscacloud/image/upload/v1672697217/goodfood/lasagna-e_rmxwqx.png",
        "price": 203
    },    
    {
        "id":9,
        "category":"drink",
        "type":"beer",
        "name": "random food name",
        "description":"small description of the food plus the ingredients ingredient 1, ingredient 2, ingredient 3, ingredient 4, etc...",
        "ingredients": [
            "sdad",
            "asdasd",
            "sadasdsa",
            "asdasd"
        ],
        "imgURL": "https://res.cloudinary.com/ivanscacloud/image/upload/v1672697212/goodfood/beer1-e_esbtww.png",
        "price": 203
    },    
    {
        "id":10,
        "category":"drink",
        "type":"coffee",
        "name": "random food name",
        "description":"small description of the food plus the ingredients ingredient 1, ingredient 2, ingredient 3, ingredient 4, etc...",
        "ingredients": [
            "sdad",
            "asdasd",
            "sadasdsa",
            "asdasd"
        ],
        "imgURL": "https://res.cloudinary.com/ivanscacloud/image/upload/v1672697212/goodfood/coffee1-e_xjbmuo.png",
        "price": 203
    },    
    {
        "id":11,
        "category":"dessert",
        "type":"smoothie",
        "name": "random food name",
        "description":"small description of the food plus the ingredients ingredient 1, ingredient 2, ingredient 3, ingredient 4, etc...",
        "ingredients": [
            "sdad",
            "asdasd",
            "sadasdsa",
            "asdasd"
        ],
        "imgURL": "https://res.cloudinary.com/ivanscacloud/image/upload/v1672697216/goodfood/jucie2-e_p2ggae.png",
        "price": 203
    },    
    {
        "id":12,
        "category":"drink",
        "type":"juice",
        "name": "random food name",
        "description":"small description of the food plus the ingredients ingredient 1, ingredient 2, ingredient 3, ingredient 4, etc...",
        "ingredients": [
            "sdad",
            "asdasd",
            "sadasdsa",
            "asdasd"
        ],
        "imgURL": "https://res.cloudinary.com/ivanscacloud/image/upload/v1672697216/goodfood/juce1-e_bnorge.png",
        "price": 203
    },    
    {
        "id":13,
        "category":"dessert",
        "type":"ice cream",
        "name": "random food name",
        "description":"small description of the food plus the ingredients ingredient 1, ingredient 2, ingredient 3, ingredient 4, etc...",
        "ingredients": [
            "sdad",
            "asdasd",
            "sadasdsa",
            "asdasd"
        ],
        "imgURL": "https://res.cloudinary.com/ivanscacloud/image/upload/v1672697216/goodfood/dessert2-e_o7yl12.png",
        "price": 203
    },    
    {
        "id":14,
        "category":"food",
        "type":"salad",
        "name": "random food name",
        "description":"small description of the food plus the ingredients ingredient 1, ingredient 2, ingredient 3, ingredient 4, etc...",
        "ingredients": [
            "sdad",
            "asdasd",
            "sadasdsa",
            "asdasd"
        ],
        "imgURL": "https://res.cloudinary.com/ivanscacloud/image/upload/v1672697221/goodfood/salad-e_wfk8cx.png",
        "price": 203
    },
    {
        "id":15,
        "category":"food",
        "type":"pasta",
        "name": "random food name",
        "description":"small description of the food plus the ingredients ingredient 1, ingredient 2, ingredient 3, ingredient 4, etc...",
        "ingredients": [
            "sdad",
            "asdasd",
            "sadasdsa",
            "asdasd"
        ],
        "imgURL": "https://res.cloudinary.com/ivanscacloud/image/upload/v1672697217/goodfood/lasagna-e_rmxwqx.png",
        "price": 203
    },
    {
        "id":16,
        "category":"drink",
        "type":"coffee",
        "name": "random food name",
        "description":"small description of the food plus the ingredients ingredient 1, ingredient 2, ingredient 3, ingredient 4, etc...",
        "ingredients": [
            "sdad",
            "asdasd",
            "sadasdsa",
            "asdasd"
        ],
        "imgURL": "https://res.cloudinary.com/ivanscacloud/image/upload/v1672697212/goodfood/coffee1-e_xjbmuo.png",
        "price": 203
    },    
    {
        "id":17,
        "category":"dessert",
        "type":"smoothie",
        "name": "random food name",
        "description":"small description of the food plus the ingredients ingredient 1, ingredient 2, ingredient 3, ingredient 4, etc...",
        "ingredients": [
            "sdad",
            "asdasd",
            "sadasdsa",
            "asdasd"
        ],
        "imgURL": "https://res.cloudinary.com/ivanscacloud/image/upload/v1672697216/goodfood/jucie2-e_p2ggae.png",
        "price": 203
    },    
    {
        "id":18,
        "category":"drink",
        "type":"juice",
        "name": "random food name",
        "description":"small description of the food plus the ingredients ingredient 1, ingredient 2, ingredient 3, ingredient 4, etc...",
        "ingredients": [
            "sdad",
            "asdasd",
            "sadasdsa",
            "asdasd"
        ],
        "imgURL": "https://res.cloudinary.com/ivanscacloud/image/upload/v1672697216/goodfood/juce1-e_bnorge.png",
        "price": 203
    },    
    {
        "id":19,
        "category":"dessert",
        "type":"ice cream",
        "name": "random food name",
        "description":"small description of the food plus the ingredients ingredient 1, ingredient 2, ingredient 3, ingredient 4, etc...",
        "ingredients": [
            "sdad",
            "asdasd",
            "sadasdsa",
            "asdasd"
        ],
        "imgURL": "https://res.cloudinary.com/ivanscacloud/image/upload/v1672697216/goodfood/dessert2-e_o7yl12.png",
        "price": 203
    },    
    {
        "id":20,
        "category":"food",
        "type":"salad",
        "name": "random food name",
        "description":"small description of the food plus the ingredients ingredient 1, ingredient 2, ingredient 3, ingredient 4, etc...",
        "ingredients": [
            "sdad",
            "asdasd",
            "sadasdsa",
            "asdasd"
        ],
        "imgURL": "https://res.cloudinary.com/ivanscacloud/image/upload/v1672697221/goodfood/salad-e_wfk8cx.png",
        "price": 203
    },
    {
        "id":21,
        "category":"food",
        "type":"burger",
        "name": "random food name",
        "description":"small description of the food plus the ingredients ingredient 1, ingredient 2, ingredient 3, ingredient 4, etc...",       
        "imgURL": "https://res.cloudinary.com/ivanscacloud/image/upload/v1672697215/goodfood/hamburger-e_kuxcuc.png",
        "price": 123
    },
    {
        "id":22,
        "category":"food",
        "type":"pizza",
        "name": "random food name",
        "description":"small description of the food plus the ingredients ingredient 1, ingredient 2, ingredient 3, ingredient 4, etc...",
        "ingredients": [
            "sdad",
            "asdasd",
            "sadasdsa",
            "asdasd"
        ],
        "imgURL": "https://res.cloudinary.com/ivanscacloud/image/upload/v1672697220/goodfood/pizza-e_lxdigr.png",
        "price": 435
    },
    {
        "id":23,
        "category":"food",
        "type":"pizza",
        "name": "random food name",
        "description":"small description of the food plus the ingredients ingredient 1, ingredient 2, ingredient 3, ingredient 4, etc...",
        "ingredients": [
            "sdad",
            "asdasd",
            "sadasdsa",
            "asdasd"
        ],
        "imgURL": "https://res.cloudinary.com/ivanscacloud/image/upload/v1672697220/goodfood/pizza-e_lxdigr.png",
        "price": 100
    },
    {
        "id":24,
        "category":"dessert",
        "type":"sundae",
        "name": "random food name",
        "description":"small description of the food plus the ingredients ingredient 1, ingredient 2, ingredient 3, ingredient 4, etc...",
        "ingredients": [
            "sdad",
            "asdasd",
            "sadasdsa",
            "asdasd"
        ],
        "imgURL": "https://res.cloudinary.com/ivanscacloud/image/upload/v1672697217/goodfood/dessert-e_a00x8q.png",
        "price": 178
    },
    {
        "id":25,
        "category":"drink",
        "type":"beer",
        "name": "random food name",
        "description":"small description of the food plus the ingredients ingredient 1, ingredient 2, ingredient 3, ingredient 4, etc...",
        "ingredients": [
            "sdad",
            "asdasd",
            "sadasdsa",
            "asdasd"
        ],
        "imgURL": "https://res.cloudinary.com/ivanscacloud/image/upload/v1672697212/goodfood/beer2-e_zmiacq.png",
        "price": 20
    },
    {
        "id":26,
        "category":"drink",
        "type":"beer",
        "name": "random food name",
        "description":"small description of the food plus the ingredients ingredient 1, ingredient 2, ingredient 3, ingredient 4, etc...",
        "ingredients": [
            "sdad",
            "asdasd",
            "sadasdsa",
            "asdasd"
        ],
        "imgURL": "https://res.cloudinary.com/ivanscacloud/image/upload/v1672697212/goodfood/beer3-e_babbne.png",
        "price": 5
    },
    {
        "id":27,
        "category":"food",
        "type":"burger",
        "name": "random food name",
        "description":"small description of the food plus the ingredients ingredient 1, ingredient 2, ingredient 3, ingredient 4, etc...",
        "ingredients": [
            "sdad",
            "asdasd",
            "sadasdsa",
            "asdasd"
        ],          
        "imgURL": "https://res.cloudinary.com/ivanscacloud/image/upload/v1672697212/goodfood/burger2-e_mcu2e2.png",
        "price": 399
    },
    {
        "id":28,
        "category":"food",
        "type":"burger",
        "name": "random food name",
        "description":"small description of the food plus the ingredients ingredient 1, ingredient 2, ingredient 3, ingredient 4, etc...",
        "ingredients": [
            "sdad",
            "asdasd",
            "sadasdsa",
            "asdasd"
        ],          
        "imgURL": "https://res.cloudinary.com/ivanscacloud/image/upload/v1672697212/goodfood/burger-e_berlqy.png",
        "price": 123
    },    
    {
        "id":29,
        "category":"food",
        "type":"pasta",
        "name": "random food name",
        "description":"small description of the food plus the ingredients ingredient 1, ingredient 2, ingredient 3, ingredient 4, etc...",
        "ingredients": [
            "sdad",
            "asdasd",
            "sadasdsa",
            "asdasd"
        ],
        "imgURL": "https://res.cloudinary.com/ivanscacloud/image/upload/v1672697217/goodfood/lasagna-e_rmxwqx.png",
        "price": 700
    },    
    {
        "id":30,
        "category":"drink",
        "type":"beer",
        "name": "random food name",
        "description":"small description of the food plus the ingredients ingredient 1, ingredient 2, ingredient 3, ingredient 4, etc...",
        "ingredients": [
            "sdad",
            "asdasd",
            "sadasdsa",
            "asdasd"
        ],
        "imgURL": "https://res.cloudinary.com/ivanscacloud/image/upload/v1672697212/goodfood/beer1-e_esbtww.png",
        "price": 99
    },    
    {
        "id":31,
        "category":"drink",
        "type":"coffee",
        "name": "random food name",
        "description":"small description of the food plus the ingredients ingredient 1, ingredient 2, ingredient 3, ingredient 4, etc...",
        "ingredients": [
            "sdad",
            "asdasd",
            "sadasdsa",
            "asdasd"
        ],
        "imgURL": "https://res.cloudinary.com/ivanscacloud/image/upload/v1672697212/goodfood/coffee1-e_xjbmuo.png",
        "price": 20
    },    
    {
        "id":32,
        "category":"dessert",
        "type":"smoothie",
        "name": "random food name",
        "description":"small description of the food plus the ingredients ingredient 1, ingredient 2, ingredient 3, ingredient 4, etc...",
        "ingredients": [
            "sdad",
            "asdasd",
            "sadasdsa",
            "asdasd"
        ],
        "imgURL": "https://res.cloudinary.com/ivanscacloud/image/upload/v1672697216/goodfood/jucie2-e_p2ggae.png",
        "price": 203
    },    
    {
        "id":33,
        "category":"drink",
        "type":"juice",
        "name": "random food name",
        "description":"small description of the food plus the ingredients ingredient 1, ingredient 2, ingredient 3, ingredient 4, etc...",
        "ingredients": [
            "sdad",
            "asdasd",
            "sadasdsa",
            "asdasd"
        ],
        "imgURL": "https://res.cloudinary.com/ivanscacloud/image/upload/v1672697216/goodfood/juce1-e_bnorge.png",
        "price": 203
    },    
    {
        "id":34,
        "category":"dessert",
        "type":"ice cream",
        "name": "random food name",
        "description":"small description of the food plus the ingredients ingredient 1, ingredient 2, ingredient 3, ingredient 4, etc...",
        "ingredients": [
            "sdad",
            "asdasd",
            "sadasdsa",
            "asdasd"
        ],
        "imgURL": "https://res.cloudinary.com/ivanscacloud/image/upload/v1672697216/goodfood/dessert2-e_o7yl12.png",
        "price": 203
    },    
    {
        "id":35,
        "category":"food",
        "type":"salad",
        "name": "random food name",
        "description":"small description of the food plus the ingredients ingredient 1, ingredient 2, ingredient 3, ingredient 4, etc...",
        "ingredients": [
            "sdad",
            "asdasd",
            "sadasdsa",
            "asdasd"
        ],
        "imgURL": "https://res.cloudinary.com/ivanscacloud/image/upload/v1672697221/goodfood/salad-e_wfk8cx.png",
        "price": 203
    },
    {
        "id":36,
        "category":"food",
        "type":"pasta",
        "name": "random food name",
        "description":"small description of the food plus the ingredients ingredient 1, ingredient 2, ingredient 3, ingredient 4, etc...",
        "ingredients": [
            "sdad",
            "asdasd",
            "sadasdsa",
            "asdasd"
        ],
        "imgURL": "https://res.cloudinary.com/ivanscacloud/image/upload/v1672697217/goodfood/lasagna-e_rmxwqx.png",
        "price": 203
    },
    {
        "id":37,
        "category":"drink",
        "type":"coffee",
        "name": "random food name",
        "description":"small description of the food plus the ingredients ingredient 1, ingredient 2, ingredient 3, ingredient 4, etc...",
        "ingredients": [
            "sdad",
            "asdasd",
            "sadasdsa",
            "asdasd"
        ],
        "imgURL": "https://res.cloudinary.com/ivanscacloud/image/upload/v1672697212/goodfood/coffee1-e_xjbmuo.png",
        "price": 203
    },    
    {
        "id":38,
        "category":"dessert",
        "type":"smoothie",
        "name": "random food name",
        "description":"small description of the food plus the ingredients ingredient 1, ingredient 2, ingredient 3, ingredient 4, etc...",
        "ingredients": [
            "sdad",
            "asdasd",
            "sadasdsa",
            "asdasd"
        ],
        "imgURL": "https://res.cloudinary.com/ivanscacloud/image/upload/v1672697216/goodfood/jucie2-e_p2ggae.png",
        "price": 203
    },    
    {
        "id":39,
        "category":"drink",
        "type":"juice",
        "name": "random food name",
        "description":"small description of the food plus the ingredients ingredient 1, ingredient 2, ingredient 3, ingredient 4, etc...",
        "ingredients": [
            "sdad",
            "asdasd",
            "sadasdsa",
            "asdasd"
        ],
        "imgURL": "https://res.cloudinary.com/ivanscacloud/image/upload/v1672697216/goodfood/juce1-e_bnorge.png",
        "price": 203
    },    
    {
        "id":40,
        "category":"dessert",
        "type":"ice cream",
        "name": "random food name",
        "description":"small description of the food plus the ingredients ingredient 1, ingredient 2, ingredient 3, ingredient 4, etc...",
        "ingredients": [
            "sdad",
            "asdasd",
            "sadasdsa",
            "asdasd"
        ],
        "imgURL": "https://res.cloudinary.com/ivanscacloud/image/upload/v1672697216/goodfood/dessert2-e_o7yl12.png",
        "price": 666
    },    
    {
        "id":41,
        "category":"food",
        "type":"salad",
        "name": "random food name",
        "description":"small description of the food plus the ingredients ingredient 1, ingredient 2, ingredient 3, ingredient 4, etc...",
        "ingredients": [
            "sdad",
            "asdasd",
            "sadasdsa",
            "asdasd"
        ],
        "imgURL": "https://res.cloudinary.com/ivanscacloud/image/upload/v1672697221/goodfood/salad-e_wfk8cx.png",
        "price": 69
    },
    {
        "id":42,
        "category":"food",
        "type":"burger",
        "name": "random food name",
        "description":"small description of the food plus the ingredients ingredient 1, ingredient 2, ingredient 3, ingredient 4, etc...",       
        "imgURL": "https://res.cloudinary.com/ivanscacloud/image/upload/v1672697215/goodfood/hamburger-e_kuxcuc.png",
        "price": 123
    },
    {
        "id":43,
        "category":"food",
        "type":"pizza",
        "name": "random food name",
        "description":"small description of the food plus the ingredients ingredient 1, ingredient 2, ingredient 3, ingredient 4, etc...",
        "ingredients": [
            "sdad",
            "asdasd",
            "sadasdsa",
            "asdasd"
        ],
        "imgURL": "https://res.cloudinary.com/ivanscacloud/image/upload/v1672697220/goodfood/pizza-e_lxdigr.png",
        "price": 435
    },
    {
        "id":45,
        "category":"food",
        "type":"pizza",
        "name": "random food name",
        "description":"small description of the food plus the ingredients ingredient 1, ingredient 2, ingredient 3, ingredient 4, etc...",
        "ingredients": [
            "sdad",
            "asdasd",
            "sadasdsa",
            "asdasd"
        ],
        "imgURL": "https://res.cloudinary.com/ivanscacloud/image/upload/v1672697220/goodfood/pizza-e_lxdigr.png",
        "price": 111
    },
    {
        "id":46,
        "category":"dessert",
        "type":"sundae",
        "name": "random food name",
        "description":"small description of the food plus the ingredients ingredient 1, ingredient 2, ingredient 3, ingredient 4, etc...",
        "ingredients": [
            "sdad",
            "asdasd",
            "sadasdsa",
            "asdasd"
        ],
        "imgURL": "https://res.cloudinary.com/ivanscacloud/image/upload/v1672697217/goodfood/dessert-e_a00x8q.png",
        "price": 178
    },
    {
        "id":47,
        "category":"drink",
        "type":"beer",
        "name": "random food name",
        "description":"small description of the food plus the ingredients ingredient 1, ingredient 2, ingredient 3, ingredient 4, etc...",
        "ingredients": [
            "sdad",
            "asdasd",
            "sadasdsa",
            "asdasd"
        ],
        "imgURL": "https://res.cloudinary.com/ivanscacloud/image/upload/v1672697212/goodfood/beer2-e_zmiacq.png",
        "price": 20
    },
    {
        "id":48,
        "category":"drink",
        "type":"beer",
        "name": "random food name",
        "description":"small description of the food plus the ingredients ingredient 1, ingredient 2, ingredient 3, ingredient 4, etc...",
        "ingredients": [
            "sdad",
            "asdasd",
            "sadasdsa",
            "asdasd"
        ],
        "imgURL": "https://res.cloudinary.com/ivanscacloud/image/upload/v1672697212/goodfood/beer3-e_babbne.png",
        "price": 20
    },
    {
        "id":49,
        "category":"food",
        "type":"burger",
        "name": "random food name",
        "description":"small description of the food plus the ingredients ingredient 1, ingredient 2, ingredient 3, ingredient 4, etc...",
        "ingredients": [
            "sdad",
            "asdasd",
            "sadasdsa",
            "asdasd"
        ],          
        "imgURL": "https://res.cloudinary.com/ivanscacloud/image/upload/v1672697212/goodfood/burger2-e_mcu2e2.png",
        "price": 123
    },
    {
        "id":50,
        "category":"food",
        "type":"burger",
        "name": "random food name",
        "description":"small description of the food plus the ingredients ingredient 1, ingredient 2, ingredient 3, ingredient 4, etc...",
        "ingredients": [
            "sdad",
            "asdasd",
            "sadasdsa",
            "asdasd"
        ],          
        "imgURL": "https://res.cloudinary.com/ivanscacloud/image/upload/v1672697212/goodfood/burger-e_berlqy.png",
        "price": 123
    },    
    {
        "id":51,
        "category":"food",
        "type":"pasta",
        "name": "random food name",
        "description":"small description of the food plus the ingredients ingredient 1, ingredient 2, ingredient 3, ingredient 4, etc...",
        "ingredients": [
            "sdad",
            "asdasd",
            "sadasdsa",
            "asdasd"
        ],
        "imgURL": "https://res.cloudinary.com/ivanscacloud/image/upload/v1672697217/goodfood/lasagna-e_rmxwqx.png",
        "price": 203
    },    
    {
        "id":52,
        "category":"drink",
        "type":"beer",
        "name": "random food name",
        "description":"small description of the food plus the ingredients ingredient 1, ingredient 2, ingredient 3, ingredient 4, etc...",
        "ingredients": [
            "sdad",
            "asdasd",
            "sadasdsa",
            "asdasd"
        ],
        "imgURL": "https://res.cloudinary.com/ivanscacloud/image/upload/v1672697212/goodfood/beer1-e_esbtww.png",
        "price": 203
    },    
    {
        "id":53,
        "category":"drink",
        "type":"coffee",
        "name": "random food name",
        "description":"small description of the food plus the ingredients ingredient 1, ingredient 2, ingredient 3, ingredient 4, etc...",
        "ingredients": [
            "sdad",
            "asdasd",
            "sadasdsa",
            "asdasd"
        ],
        "imgURL": "https://res.cloudinary.com/ivanscacloud/image/upload/v1672697212/goodfood/coffee1-e_xjbmuo.png",
        "price": 203
    },    
    {
        "id":54,
        "category":"dessert",
        "type":"smoothie",
        "name": "random food name",
        "description":"small description of the food plus the ingredients ingredient 1, ingredient 2, ingredient 3, ingredient 4, etc...",
        "ingredients": [
            "sdad",
            "asdasd",
            "sadasdsa",
            "asdasd"
        ],
        "imgURL": "https://res.cloudinary.com/ivanscacloud/image/upload/v1672697216/goodfood/jucie2-e_p2ggae.png",
        "price": 203
    },    
    {
        "id":55,
        "category":"drink",
        "type":"juice",
        "name": "random food name",
        "description":"small description of the food plus the ingredients ingredient 1, ingredient 2, ingredient 3, ingredient 4, etc...",
        "ingredients": [
            "sdad",
            "asdasd",
            "sadasdsa",
            "asdasd"
        ],
        "imgURL": "https://res.cloudinary.com/ivanscacloud/image/upload/v1672697216/goodfood/juce1-e_bnorge.png",
        "price": 203
    },    
    {
        "id":56,
        "category":"dessert",
        "type":"ice cream",
        "name": "random food name",
        "description":"small description of the food plus the ingredients ingredient 1, ingredient 2, ingredient 3, ingredient 4, etc...",
        "ingredients": [
            "sdad",
            "asdasd",
            "sadasdsa",
            "asdasd"
        ],
        "imgURL": "https://res.cloudinary.com/ivanscacloud/image/upload/v1672697216/goodfood/dessert2-e_o7yl12.png",
        "price": 54
    },    
    {
        "id":57,
        "category":"food",
        "type":"salad",
        "name": "random food name",
        "description":"small description of the food plus the ingredients ingredient 1, ingredient 2, ingredient 3, ingredient 4, etc...",
        "ingredients": [
            "sdad",
            "asdasd",
            "sadasdsa",
            "asdasd"
        ],
        "imgURL": "https://res.cloudinary.com/ivanscacloud/image/upload/v1672697221/goodfood/salad-e_wfk8cx.png",
        "price": 203
    },
    {
        "id":58,
        "category":"food",
        "type":"pasta",
        "name": "random food name",
        "description":"small description of the food plus the ingredients ingredient 1, ingredient 2, ingredient 3, ingredient 4, etc...",
        "ingredients": [
            "sdad",
            "asdasd",
            "sadasdsa",
            "asdasd"
        ],
        "imgURL": "https://res.cloudinary.com/ivanscacloud/image/upload/v1672697217/goodfood/lasagna-e_rmxwqx.png",
        "price": 203
    },
    {
        "id":59,
        "category":"drink",
        "type":"coffee",
        "name": "random food name",
        "description":"small description of the food plus the ingredients ingredient 1, ingredient 2, ingredient 3, ingredient 4, etc...",
        "ingredients": [
            "sdad",
            "asdasd",
            "sadasdsa",
            "asdasd"
        ],
        "imgURL": "https://res.cloudinary.com/ivanscacloud/image/upload/v1672697212/goodfood/coffee1-e_xjbmuo.png",
        "price": 203
    },    
    {
        "id":60,
        "category":"dessert",
        "type":"smoothie",
        "name": "random food name",
        "description":"small description of the food plus the ingredients ingredient 1, ingredient 2, ingredient 3, ingredient 4, etc...",
        "ingredients": [
            "sdad",
            "asdasd",
            "sadasdsa",
            "asdasd"
        ],
        "imgURL": "https://res.cloudinary.com/ivanscacloud/image/upload/v1672697216/goodfood/jucie2-e_p2ggae.png",
        "price": 203
    },    
    {
        "id":61,
        "category":"drink",
        "type":"juice",
        "name": "random food name",
        "description":"small description of the food plus the ingredients ingredient 1, ingredient 2, ingredient 3, ingredient 4, etc...",
        "ingredients": [
            "sdad",
            "asdasd",
            "sadasdsa",
            "asdasd"
        ],
        "imgURL": "https://res.cloudinary.com/ivanscacloud/image/upload/v1672697216/goodfood/juce1-e_bnorge.png",
        "price": 203
    },    
    {
        "id":62,
        "category":"dessert",
        "type":"ice cream",
        "name": "random food name",
        "description":"small description of the food plus the ingredients ingredient 1, ingredient 2, ingredient 3, ingredient 4, etc...",
        "ingredients": [
            "sdad",
            "asdasd",
            "sadasdsa",
            "asdasd"
        ],
        "imgURL": "https://res.cloudinary.com/ivanscacloud/image/upload/v1672697216/goodfood/dessert2-e_o7yl12.png",
        "price": 0
    },    
    {
        "id":63,
        "category":"food",
        "type":"salad",
        "name": "random food name",
        "description":"small description of the food plus the ingredients ingredient 1, ingredient 2, ingredient 3, ingredient 4, etc...",
        "ingredients": [
            "sdad",
            "asdasd",
            "sadasdsa",
            "asdasd"
        ],
        "imgURL": "https://res.cloudinary.com/ivanscacloud/image/upload/v1672697221/goodfood/salad-e_wfk8cx.png",
        "price": 30
    }
        
        

    
]